pyheos/__init__.py
pyheos/abc.py
pyheos/common.py
pyheos/connection.py
pyheos/const.py
pyheos/credentials.py
pyheos/dispatch.py
pyheos/error.py
pyheos/group.py
pyheos/heos.py
pyheos/media.py
pyheos/message.py
pyheos/options.py
pyheos/player.py
pyheos/py.typed
pyheos/search.py
pyheos/system.py
pyheos/types.py
pyheos/command/__init__.py
pyheos/command/browse.py
pyheos/command/connection.py
pyheos/command/group.py
pyheos/command/player.py
pyheos/command/system.py
pyheos/util/__init__.py
pyheos/util/mediauri.py
pyheos-1.0.6.dist-info/licenses/LICENSE
pyheos-1.0.6.dist-info/METADATA
pyheos-1.0.6.dist-info/WHEEL
pyheos-1.0.6.dist-info/top_level.txt
pyheos-1.0.6.dist-info/RECORD
