Metadata-Version: 2.4
Name: pyheos
Version: 1.0.6
Summary: An async python library for controlling HEOS devices through the HEOS CLI Protocol
Author-email: Andrew Sayre <andrew@sayre.net>
License-Expression: Apache-2.0
Project-URL: Source Code, https://github.com/andrewsayre/pyheos
Keywords: heos,dennon,maranz
Platform: any
Classifier: Development Status :: 5 - Production/Stable
Classifier: Intended Audience :: Developers
Classifier: Operating System :: OS Independent
Classifier: Topic :: Software Development :: Libraries
Classifier: Topic :: Home Automation
Classifier: Programming Language :: Python :: 3.11
Classifier: Programming Language :: Python :: 3.12
Classifier: Programming Language :: Python :: 3.13
Requires-Python: >=3.11
License-File: LICENSE
Dynamic: license-file
